HDL/RTL/uart_tx.vhd
--! @file       uart_tx.vhd
--! @brief      UART transmitter FSM
--! @details    Generates UART TX signaling when a data (iData) is provided
--!             with a request signal (iReq). When the transmission is started,
--!             an acknowledgement (oAck) signal is generated. The next data
--!             then can be supplied after this ack signal.
--! @author     Selman Ergunay
--! @date       2020-10-20

-- WORD_NBITS : "00"=>5, "01"=>6, "10"=>7, "11"=>8
-- STOP_NBITS : "00"=>1, "01"=>1, "10"=>2, "11"=>1.5
-- PARITY     : "0X"=>No parity,  "10"=>Even parity, "11"=>Odd parity
-- BAUD       : "000"=>1200, "001"=>2400, "010"=>4800, "011"=>9600
--              "100"=>19200, "101"=>38400,"110"=>57600, "111"=>115200

----------------------------------------------------------------------------
library ieee;
use ieee.std_logic_1164.all;
use ieee.numeric_std.all;

----------------------------------------------------------------------------
entity uart_tx is
	port(
		iClk       : in std_logic;  --! System clock, 12 MHz
		iRst       : in std_logic;  --! System reset
		-- Control pins
		iBaud      : in std_logic_vector(2 downto 0);
		iParity_en : in std_logic;
		iParity    : in std_logic;  --! 0: even, 1:odd
		iWord_len  : in std_logic_vector(1 downto 0);
		iStop_len  : in std_logic;

		iReq       : in std_logic;  --! Tx request
		iData      : in std_logic_vector(7 downto 0);
		oAck       : out std_logic;
		oTx        : out std_logic);
end entity uart_tx;

----------------------------------------------------------------------------
architecture rtl of uart_tx is

	constant C_BAUD_CNT_NBITS : integer := 12;

	signal baud_cnt_limit  : unsigned(C_BAUD_CNT_NBITS-1 downto 0) := (others=>'0');
	signal baud_cnt        : unsigned(C_BAUD_CNT_NBITS-1 downto 0) := (others=>'0');
	signal baud_en         : std_logic := '0';

	signal word_nbits      : unsigned(3 downto 0) := (others=>'0');

	signal data_in_next    : std_logic_vector(7 downto 0) := (others=>'0');
	signal data_in_reg     : std_logic_vector(7 downto 0) := (others=>'0');
	signal nbits_left_next : unsigned(3 downto 0) := (others=>'0');
	signal nbits_left_reg  : unsigned(3 downto 0) := (others=>'0');

	signal baud_tick      : std_logic := '0'; --! Baud ticks at desired baud rate

	signal tx_next        : std_logic := '0';
	signal tx_reg         : std_logic := '0';

	signal start_next     : std_logic := '0';
	signal start_reg      : std_logic := '0';

	signal parity_next    : std_logic := '0';
	signal parity_reg     : std_logic := '0';

	signal req            : std_logic := '0';
	signal ack            : std_logic := '0';

	type fsm_states is(
		ST_START,
		ST_TX_DATA,
		ST_PARITY,
		ST_STOP,
	   	ST_STOP_EXT);

	signal state_next, state_reg 	: fsm_states := ST_START;

begin

	-- BAUD       : "000"=>1200, "001"=>2400, "010"=>4800, "011"=>9600
	--              "100"=>19200, "101"=>38400,"110"=>57600, "111"=>115200
	baud_cnt_limit <= to_unsigned(10000, C_BAUD_CNT_NBITS) when iBaud = "000" else
					  to_unsigned( 5000, C_BAUD_CNT_NBITS) when iBaud = "001" else
					  to_unsigned( 2500, C_BAUD_CNT_NBITS) when iBaud = "010" else
					  to_unsigned( 1250, C_BAUD_CNT_NBITS) when iBaud = "011" else
					  to_unsigned(  625, C_BAUD_CNT_NBITS) when iBaud = "100" else
					  to_unsigned(  312, C_BAUD_CNT_NBITS) when iBaud = "101" else
					  to_unsigned(  208, C_BAUD_CNT_NBITS) when iBaud = "110" else
					  to_unsigned(  104, C_BAUD_CNT_NBITS) when iBaud = "111";

	-- WORD_NBITS : "00"=>5, "01"=>6, "10"=>7, "11"=>8
	word_nbits <= to_unsigned(4, 4) when iWord_len = "00" else
			      to_unsigned(5, 4) when iWord_len = "01" else
				  to_unsigned(6, 4) when iWord_len = "10" else
				  to_unsigned(7, 4) when iWord_len = "11";


	BAUD_CNT_PROC: process(iClk)
	begin
		if rising_edge(iClk) then
			if iRst = '1' or baud_cnt = baud_cnt_limit-1 or baud_en = '0' then
				 baud_cnt <= (others=>'0');
			else
				 baud_cnt <= baud_cnt + 1;
			end if;
		end if;
	end process BAUD_CNT_PROC;

	-- Generate baud tick
	baud_tick <= '1' when baud_cnt = baud_cnt_limit-1 else
				 '0';

	START_PROC: process(iClk)
	begin
		if rising_edge(iClk) then
			if iRst = '1'then
				start_reg <= '0';
			else
				start_reg <= start_next;
			end if;
		end if;
	end process START_PROC;

	--! Request input register process
	REQ_REG_PROC: process(iClk)
	begin
		if rising_edge(iClk) then
			if iRst = '1'then
				req <= '0';
			else
				req <= iReq;
			end if;
		end if;
	end process REQ_REG_PROC;


	DATA_IN_REG_PROC: process(iClk)
	begin
		if rising_edge(iClk) then
			if iRst = '1'then
				data_in_reg <= (others=>'0');
			else
				data_in_reg <= data_in_next;
			end if;
		end if;
	end process DATA_IN_REG_PROC;

	NBITS_LEFT_PROC: process(iClk)
	begin
		if rising_edge(iClk) then
			if iRst = '1'then
				nbits_left_reg <= word_nbits;
			else
				nbits_left_reg <= nbits_left_next;
			end if;
		end if;
	end process NBITS_LEFT_PROC;

	PARITY_REG_PROC: process(iClk)
	begin
		if rising_edge(iClk) then
			if iRst = '1'then
				parity_reg <= '0';
			else
				parity_reg <= parity_next;
			end if;
		end if;
	end process PARITY_REG_PROC;



----------------------------------------------------------------------------

	--! FSM state register
	FSM_STATE_REG : process(iClk)
	begin
		if rising_edge(iClk) then
			if iRst = '1' then
				state_reg 		<= ST_START;
			else
				state_reg 		<= state_next;
			end if;
		end if;
	end process FSM_STATE_REG;

	FSM_NSL: process(state_reg, baud_tick, data_in_reg, nbits_left_reg, req, start_reg, parity_reg)
	begin
		state_next 	    <= state_reg;
		tx_next         <= tx_reg;
		start_next      <= start_reg;
		data_in_next    <= data_in_reg;
		nbits_left_next <= nbits_left_reg;
		ack             <= '0';
		parity_next     <= parity_reg;
		baud_en         <= '1';

		case state_reg is

			when ST_START		=>

				if req = '1' then
					tx_next      <= '0';
					data_in_next <= iData;
				else
					baud_en      <= '0';
				end if;

				if baud_tick = '1' then
					state_next 	 <= ST_TX_DATA;
					ack          <= '1';
				end if;

			---------------------------------------------------

			when ST_TX_DATA	=>

				tx_next         <= data_in_reg(0);

				if baud_tick = '1' then

					parity_next     <= parity_reg xor data_in_reg(0);

					data_in_next    <= '0' & data_in_reg(7 downto 1);
					nbits_left_next <= nbits_left_reg - 1;

					if nbits_left_reg = 0 then

						nbits_left_next <= word_nbits;
						if iParity_en = '1' then
							state_next	<= ST_PARITY;
						else
							state_next	<= ST_STOP;
						end if;
					end if;
				end if;

			---------------------------------------------------
			when ST_PARITY =>

				tx_next     <= iParity xor parity_reg;

				if baud_tick = '1' then
					parity_next <= '0';
					state_next 	<= ST_STOP;
				end if;

			---------------------------------------------------
			when ST_STOP  =>

				tx_next         <= '1';

				if baud_tick = '1' then
					if iStop_len = '0' then
				  		state_next <= ST_START;
					else
				  		state_next <= ST_STOP_EXT;
					end if;

					state_next 	<= ST_START;

				end if;

			---------------------------------------------------
			when ST_STOP_EXT  =>

				if baud_tick = '1' then
					state_next 	<= ST_START;
				end if;

		end case;

	end process FSM_NSL;

--------------------------------------------------------------------------------

	TX_REG_PROC: process(iClk)
	begin
		if rising_edge(iClk) then
			if iRst = '1'then
				tx_reg <= '1';
			else
				tx_reg <= tx_next;
			end if;
		end if;
	end process TX_REG_PROC;

	oTx  <= tx_reg;
	oAck <= ack;


--------------------------------------------------------------------------------










end architecture rtl;
----------------------------------------------------------------------------

HDL/TB/uart_tx_tb.vhd
--! @file 			uart_tx_tb.vhd
--! @brief 			a short description what can be found in the file
--! @details 		detailed description
--! @author 		Selman Ergünay
--! @date 			20.10.2020
----------------------------------------------------------------------------
library ieee;
use ieee.std_logic_1164.all;
use ieee.numeric_std.all;

library std;
use std.textio.all;

----------------------------------------------------------------------------
entity uart_tx_tb is
end entity;
----------------------------------------------------------------------------

architecture tb of uart_tx_tb is
------------------------------------------------------------------------
	component uart_tx
		generic(
			BAUD       : positive := 9600;
			DATA_NBITS : positive := 7;
			PARITY     : natural  := 0;  --! 0: no parity, 1: odd, 2: even
			STOP_NBITS : positive := 1); --! 1: 1, 2: 2, 3: 1.5
		port(
			iClk  : in std_logic;
			iRst  : in std_logic;
			iReq  : in std_logic;
			iData : in std_logic_vector(DATA_NBITS-1 downto 0);
			oAck  : out std_logic;
			oTx   : out std_logic);
	end component;

	-- Simulation constants
	constant C_CLK_PER    : time    := 83.33 ns;
	constant C_BAUD       : natural := 8;
	constant C_DATA_NBITS : natural := 8;
	constant C_PARITY     : natural := 8;
	constant C_STOP_NBITS : natural := 8;

	-- Simulation control signals
	signal sim_clk  : std_logic := '0';
	signal sim_rst  : std_logic := '0';
	signal sim_stop : boolean 	:= FALSE;		-- stop simulation?

	signal sim_req  : std_logic := '0';
	signal sim_data : std_logic_vector(C_DATA_NBITS-1 downto 0) := (others=>'0');

	signal duv_ack : std_logic := '0';
	signal duv_tx  : std_logic := '0';


begin
----------------------------------------------------------------------------

	DUV: uart_tx
		generic map(
			BAUD       => C_BAUD,
			DATA_NBITS => C_DATA_NBITS,
			PARITY     => C_PARITY,
			STOP_NBITS => C_STOP_NBITS)
		port map(
			iClk  => sim_clk,
			iRst  => sim_rst,
			iReq  => sim_req,
			iData => sim_data,
			oAck  => duv_ack,
			oTx   => duv_tx);

	CLK_STIM : sim_clk 	<= not sim_clk after C_CLK_PER/2 when not sim_stop;

	INFO_PROC: process
        variable l : line;
 	begin
		write (l, string'("Simulation started."));
        writeline (output, l);
        wait;
	end process;

	STIM_PROC: process

		procedure init is
		begin
			sim_rst 			<= '1';
			wait for 400 ns;
			sim_rst				<= '0';
		end procedure init;

		procedure uart_write(
			constant uart_tx_data : std_logic_vector(C_DATA_NBITS-1 downto 0)) is
		begin
			sim_data  <= uart_tx_data(C_DATA_NBITS-1 downto 0);
			sim_req   <= '1';

			--wait until falling_edge(duv_ack);
			wait for 1 ms;

			sim_data   <= (others=>'0');
			sim_req    <= '0';
		end procedure uart_write;

	begin
		init;
		wait for 500 ns;
		uart_write("11110000");
		wait for 1 ms;
		sim_stop 	<= True;
		wait;
	end process STIM_PROC;

----------------------------------------------------------------------------
end architecture tb;
----------------------------------------------------------------------------

GHDL/uart_tx_tb/sim/uart_tx_tb.vcd
$date
  Sat Oct 24 21:31:20 2020
$end
$version
  GHDL v0
$end
$timescale
  1 fs
$end
$scope module standard $end
$upscope $end
$scope module std_logic_1164 $end
$upscope $end
$scope module numeric_std $end
$upscope $end
$scope module textio $end
$upscope $end
$scope module uart_tx_tb $end
$var reg 1 ! sim_clk $end
$var reg 1 " sim_rst $end
$var reg 1 # sim_stop $end
$var reg 1 $ sim_req $end
$var reg 8 % sim_data[7:0] $end
$var reg 1 & duv_ack $end
$var reg 1 ' duv_tx $end
$scope module duv $end
$var reg 1 ( iclk $end
$var reg 1 ) irst $end
$var reg 1 * ireq $end
$var reg 8 + idata[7:0] $end
$var reg 1 , oack $end
$var reg 1 - otx $end
$var reg 12 . baud_cnt_limit[11:0] $end
$var reg 12 / baud_cnt[11:0] $end
$var reg 1 0 baud_tick $end
$comment state_next is not handled $end
$comment state_reg is not handled $end
$upscope $end
$upscope $end
$enddefinitions $end
#0
0!
1"
0#
0$
b00000000 %
U&
U'
0(
1)
0*
b00000000 +
U,
U-
b010011100010 .
bUUUUUUUUUUUU /
00
#41665000
1!
1(
b000000000000 /
#83330000
0!
0(
#124995000
1!
1(
#166660000
0!
0(
#208325000
1!
1(
#249990000
0!
0(
#291655000
1!
1(
#333320000
0!
0(
#374985000
1!
1(
#400000000
0"
0)
#416650000
0!
0(
#458315000
1!
1(
b000000000001 /
#499980000
0!
0(
#541645000
1!
1(
b000000000010 /
#583310000
0!
0(
#624975000
1!
1(
b000000000011 /
#666640000
0!
0(
#708305000
1!
1(
b000000000100 /
#749970000
0!
0(
#791635000
1!
1(
b000000000101 /
#833300000
0!
0(
#874965000
1!
1(
b000000000110 /
#900000000
1$
b11110000 %
1*
b11110000 +
#916630000
0!
0(
#958295000
1!
1(
b000000000111 /
#999960000
0!
0(
#1041625000
1!
1(
b000000001000 /
#1083290000
0!
0(
#1124955000
1!
1(
b000000001001 /
#1166620000
0!
0(
#1208285000
1!
1(
b000000001010 /
#1249950000
0!
0(
#1291615000
1!
1(
b000000001011 /
#1333280000
0!
0(
#1374945000
1!
1(
b000000001100 /
#1416610000
0!
0(
#1458275000
1!
1(
b000000001101 /
#1499940000
0!
0(
#1541605000
1!
1(
b000000001110 /
#1583270000
0!
0(
#1624935000
1!
1(
b000000001111 /
#1666600000
0!
0(
#1708265000
1!
1(
b000000010000 /
#1749930000
0!
0(
#1791595000
1!
1(
b000000010001 /
#1833260000
0!
0(
#1874925000
1!
1(
b000000010010 /
#1916590000
0!
0(
#1958255000
1!
1(
b000000010011 /
#1999920000
0!
0(
#2041585000
1!
1(
b000000010100 /
#2083250000
0!
0(
#2124915000
1!
1(
b000000010101 /
#2166580000
0!
0(
#2208245000
1!
1(
b000000010110 /
#2249910000
0!
0(
#2291575000
1!
1(
b000000010111 /
#2333240000
0!
0(
#2374905000
1!
1(
b000000011000 /
#2416570000
0!
0(
#2458235000
1!
1(
b000000011001 /
#2499900000
0!
0(
#2541565000
1!
1(
b000000011010 /
#2583230000
0!
0(
#2624895000
1!
1(
b000000011011 /
#2666560000
0!
0(
#2708225000
1!
1(
b000000011100 /
#2749890000
0!
0(
#2791555000
1!
1(
b000000011101 /
#2833220000
0!
0(
#2874885000
1!
1(
b000000011110 /
#2916550000
0!
0(
#2958215000
1!
1(
b000000011111 /
#2999880000
0!
0(
#3041545000
1!
1(
b000000100000 /
#3083210000
0!
0(
#3124875000
1!
1(
b000000100001 /
#3166540000
0!
0(
#3208205000
1!
1(
b000000100010 /
#3249870000
0!
0(
#3291535000
1!
1(
b000000100011 /
#3333200000
0!
0(
#3374865000
1!
1(
b000000100100 /
#3416530000
0!
0(
#3458195000
1!
1(
b000000100101 /
#3499860000
0!
0(
#3541525000
1!
1(
b000000100110 /
#3583190000
0!
0(
#3624855000
1!
1(
b000000100111 /
#3666520000
0!
0(
#3708185000
1!
1(
b000000101000 /
#3749850000
0!
0(
#3791515000
1!
1(
b000000101001 /
#3833180000
0!
0(
#3874845000
1!
1(
b000000101010 /
#3916510000
0!
0(
#3958175000
1!
1(
b000000101011 /
#3999840000
0!
0(
#4041505000
1!
1(
b000000101100 /
#4083170000
0!
0(
#4124835000
1!
1(
b000000101101 /
#4166500000
0!
0(
#4208165000
1!
1(
b000000101110 /
#4249830000
0!
0(
#4291495000
1!
1(
b000000101111 /
#4333160000
0!
0(
#4374825000
1!
1(
b000000110000 /
#4416490000
0!
0(
#4458155000
1!
1(
b000000110001 /
#4499820000
0!
0(
#4541485000
1!
1(
b000000110010 /
#4583150000
0!
0(
#4624815000
1!
1(
b000000110011 /
#4666480000
0!
0(
#4708145000
1!
1(
b000000110100 /
#4749810000
0!
0(
#4791475000
1!
1(
b000000110101 /
#4833140000
0!
0(
#4874805000
1!
1(
b000000110110 /
#4916470000
0!
0(
#4958135000
1!
1(
b000000110111 /
#4999800000
0!
0(
#5041465000
1!
1(
b000000111000 /
#5083130000
0!
0(
#5124795000
1!
1(
b000000111001 /
#5166460000
0!
0(
#5208125000
1!
1(
b000000111010 /
#5249790000
0!
0(
#5291455000
1!
1(
b000000111011 /
#5333120000
0!
0(
#5374785000
1!
1(
b000000111100 /
#5416450000
0!
0(
#5458115000
1!
1(
b000000111101 /
#5499780000
0!
0(
#5541445000
1!
1(
b000000111110 /
#5583110000
0!
0(
#5624775000
1!
1(
b000000111111 /
#5666440000
0!
0(
#5708105000
1!
1(
b000001000000 /
#5749770000
0!
0(
#5791435000
1!
1(
b000001000001 /
#5833100000
0!
0(
#5874765000
1!
1(
b000001000010 /
#5916430000
0!
0(
#5958095000
1!
1(
b000001000011 /
#5999760000
0!
0(
#6041425000
1!
1(
b000001000100 /
#6083090000
0!
0(
#6124755000
1!
1(
b000001000101 /
#6166420000
0!
0(
#6208085000
1!
1(
b000001000110 /
#6249750000
0!
0(
#6291415000
1!
1(
b000001000111 /
#6333080000
0!
0(
#6374745000
1!
1(
b000001001000 /
#6416410000
0!
0(
#6458075000
1!
1(
b000001001001 /
#6499740000
0!
0(
#6541405000
1!
1(
b000001001010 /
#6583070000
0!
0(
#6624735000
1!
1(
b000001001011 /
#6666400000
0!
0(
#6708065000
1!
1(
b000001001100 /
#6749730000
0!
0(
#6791395000
1!
1(
b000001001101 /
#6833060000
0!
0(
#6874725000
1!
1(
b000001001110 /
#6916390000
0!
0(
#6958055000
1!
1(
b000001001111 /
#6999720000
0!
0(
#7041385000
1!
1(
b000001010000 /
#7083050000
0!
0(
#7124715000
1!
1(
b000001010001 /
#7166380000
0!
0(
#7208045000
1!
1(
b000001010010 /
#7249710000
0!
0(
#7291375000
1!
1(
b000001010011 /
#7333040000
0!
0(
#7374705000
1!
1(
b000001010100 /
#7416370000
0!
0(
#7458035000
1!
1(
b000001010101 /
#7499700000
0!
0(
#7541365000
1!
1(
b000001010110 /
#7583030000
0!
0(
#7624695000
1!
1(
b000001010111 /
#7666360000
0!
0(
#7708025000
1!
1(
b000001011000 /
#7749690000
0!
0(
#7791355000
1!
1(
b000001011001 /
#7833020000
0!
0(
#7874685000
1!
1(
b000001011010 /
#7916350000
0!
0(
#7958015000
1!
1(
b000001011011 /
#7999680000
0!
0(
#8041345000
1!
1(
b000001011100 /
#8083010000
0!
0(
#8124675000
1!
1(
b000001011101 /
#8166340000
0!
0(
#8208005000
1!
1(
b000001011110 /
#8249670000
0!
0(
#8291335000
1!
1(
b000001011111 /
#8333000000
0!
0(
#8374665000
1!
1(
b000001100000 /
#8416330000
0!
0(
#8457995000
1!
1(
b000001100001 /
#8499660000
0!
0(
#8541325000
1!
1(
b000001100010 /
#8582990000
0!
0(
#8624655000
1!
1(
b000001100011 /
#8666320000
0!
0(
#8707985000
1!
1(
b000001100100 /
#8749650000
0!
0(
#8791315000
1!
1(
b000001100101 /
#8832980000
0!
0(
#8874645000
1!
1(
b000001100110 /
#8916310000
0!
0(
#8957975000
1!
1(
b000001100111 /
#8999640000
0!
0(
#9041305000
1!
1(
b000001101000 /
#9082970000
0!
0(
#9124635000
1!
1(
b000001101001 /
#9166300000
0!
0(
#9207965000
1!
1(
b000001101010 /
#9249630000
0!
0(
#9291295000
1!
1(
b000001101011 /
#9332960000
0!
0(
#9374625000
1!
1(
b000001101100 /
#9416290000
0!
0(
#9457955000
1!
1(
b000001101101 /
#9499620000
0!
0(
#9541285000
1!
1(
b000001101110 /
#9582950000
0!
0(
#9624615000
1!
1(
b000001101111 /
#9666280000
0!
0(
#9707945000
1!
1(
b000001110000 /
#9749610000
0!
0(
#9791275000
1!
1(
b000001110001 /
#9832940000
0!
0(
#9874605000
1!
1(
b000001110010 /
#9916270000
0!
0(
#9957935000
1!
1(
b000001110011 /
#9999600000
0!
0(
#10041265000
1!
1(
b000001110100 /
#10082930000
0!
0(
#10124595000
1!
1(
b000001110101 /
#10166260000
0!
0(
#10207925000
1!
1(
b000001110110 /
#10249590000
0!
0(
#10291255000
1!
1(
b000001110111 /
#10332920000
0!
0(
#10374585000
1!
1(
b000001111000 /
#10416250000
0!
0(
#10457915000
1!
1(
b000001111001 /
#10499580000
0!
0(
#10541245000
1!
1(
b000001111010 /
#10582910000
0!
0(
#10624575000
1!
1(
b000001111011 /
#10666240000
0!
0(
#10707905000
1!
1(
b000001111100 /
#10749570000
0!
0(
#10791235000
1!
1(
b000001111101 /
#10832900000
0!
0(
#10874565000
1!
1(
b000001111110 /
#10916230000
0!
0(
#10957895000
1!
1(
b000001111111 /
#10999560000
0!
0(
#11041225000
1!
1(
b000010000000 /
#11082890000
0!
0(
#11124555000
1!
1(
b000010000001 /
#11166220000
0!
0(
#11207885000
1!
1(
b000010000010 /
#11249550000
0!
0(
#11291215000
1!
1(
b000010000011 /
#11332880000
0!
0(
#11374545000
1!
1(
b000010000100 /
#11416210000
0!
0(
#11457875000
1!
1(
b000010000101 /
#11499540000
0!
0(
#11541205000
1!
1(
b000010000110 /
#11582870000
0!
0(
#11624535000
1!
1(
b000010000111 /
#11666200000
0!
0(
#11707865000
1!
1(
b000010001000 /
#11749530000
0!
0(
#11791195000
1!
1(
b000010001001 /
#11832860000
0!
0(
#11874525000
1!
1(
b000010001010 /
#11916190000
0!
0(
#11957855000
1!
1(
b000010001011 /
#11999520000
0!
0(
#12041185000
1!
1(
b000010001100 /
#12082850000
0!
0(
#12124515000
1!
1(
b000010001101 /
#12166180000
0!
0(
#12207845000
1!
1(
b000010001110 /
#12249510000
0!
0(
#12291175000
1!
1(
b000010001111 /
#12332840000
0!
0(
#12374505000
1!
1(
b000010010000 /
#12416170000
0!
0(
#12457835000
1!
1(
b000010010001 /
#12499500000
0!
0(
#12541165000
1!
1(
b000010010010 /
#12582830000
0!
0(
#12624495000
1!
1(
b000010010011 /
#12666160000
0!
0(
#12707825000
1!
1(
b000010010100 /
#12749490000
0!
0(
#12791155000
1!
1(
b000010010101 /
#12832820000
0!
0(
#12874485000
1!
1(
b000010010110 /
#12916150000
0!
0(
#12957815000
1!
1(
b000010010111 /
#12999480000
0!
0(
#13041145000
1!
1(
b000010011000 /
#13082810000
0!
0(
#13124475000
1!
1(
b000010011001 /
#13166140000
0!
0(
#13207805000
1!
1(
b000010011010 /
#13249470000
0!
0(
#13291135000
1!
1(
b000010011011 /
#13332800000
0!
0(
#13374465000
1!
1(
b000010011100 /
#13416130000
0!
0(
#13457795000
1!
1(
b000010011101 /
#13499460000
0!
0(
#13541125000
1!
1(
b000010011110 /
#13582790000
0!
0(
#13624455000
1!
1(
b000010011111 /
#13666120000
0!
0(
#13707785000
1!
1(
b000010100000 /
#13749450000
0!
0(
#13791115000
1!
1(
b000010100001 /
#13832780000
0!
0(
#13874445000
1!
1(
b000010100010 /
#13916110000
0!
0(
#13957775000
1!
1(
b000010100011 /
#13999440000
0!
0(
#14041105000
1!
1(
b000010100100 /
#14082770000
0!
0(
#14124435000
1!
1(
b000010100101 /
#14166100000
0!
0(
#14207765000
1!
1(
b000010100110 /
#14249430000
0!
0(
#14291095000
1!
1(
b000010100111 /
#14332760000
0!
0(
#14374425000
1!
1(
b000010101000 /
#14416090000
0!
0(
#14457755000
1!
1(
b000010101001 /
#14499420000
0!
0(
#14541085000
1!
1(
b000010101010 /
#14582750000
0!
0(
#14624415000
1!
1(
b000010101011 /
#14666080000
0!
0(
#14707745000
1!
1(
b000010101100 /
#14749410000
0!
0(
#14791075000
1!
1(
b000010101101 /
#14832740000
0!
0(
#14874405000
1!
1(
b000010101110 /
#14916070000
0!
0(
#14957735000
1!
1(
b000010101111 /
#14999400000
0!
0(
#15041065000
1!
1(
b000010110000 /
#15082730000
0!
0(
#15124395000
1!
1(
b000010110001 /
#15166060000
0!
0(
#15207725000
1!
1(
b000010110010 /
#15249390000
0!
0(
#15291055000
1!
1(
b000010110011 /
#15332720000
0!
0(
#15374385000
1!
1(
b000010110100 /
#15416050000
0!
0(
#15457715000
1!
1(
b000010110101 /
#15499380000
0!
0(
#15541045000
1!
1(
b000010110110 /
#15582710000
0!
0(
#15624375000
1!
1(
b000010110111 /
#15666040000
0!
0(
#15707705000
1!
1(
b000010111000 /
#15749370000
0!
0(
#15791035000
1!
1(
b000010111001 /
#15832700000
0!
0(
#15874365000
1!
1(
b000010111010 /
#15916030000
0!
0(
#15957695000
1!
1(
b000010111011 /
#15999360000
0!
0(
#16041025000
1!
1(
b000010111100 /
#16082690000
0!
0(
#16124355000
1!
1(
b000010111101 /
#16166020000
0!
0(
#16207685000
1!
1(
b000010111110 /
#16249350000
0!
0(
#16291015000
1!
1(
b000010111111 /
#16332680000
0!
0(
#16374345000
1!
1(
b000011000000 /
#16416010000
0!
0(
#16457675000
1!
1(
b000011000001 /
#16499340000
0!
0(
#16541005000
1!
1(
b000011000010 /
#16582670000
0!
0(
#16624335000
1!
1(
b000011000011 /
#16666000000
0!
0(
#16707665000
1!
1(
b000011000100 /
#16749330000
0!
0(
#16790995000
1!
1(
b000011000101 /
#16832660000
0!
0(
#16874325000
1!
1(
b000011000110 /
#16915990000
0!
0(
#16957655000
1!
1(
b000011000111 /
#16999320000
0!
0(
#17040985000
1!
1(
b000011001000 /
#17082650000
0!
0(
#17124315000
1!
1(
b000011001001 /
#17165980000
0!
0(
#17207645000
1!
1(
b000011001010 /
#17249310000
0!
0(
#17290975000
1!
1(
b000011001011 /
#17332640000
0!
0(
#17374305000
1!
1(
b000011001100 /
#17415970000
0!
0(
#17457635000
1!
1(
b000011001101 /
#17499300000
0!
0(
#17540965000
1!
1(
b000011001110 /
#17582630000
0!
0(
#17624295000
1!
1(
b000011001111 /
#17665960000
0!
0(
#17707625000
1!
1(
b000011010000 /
#17749290000
0!
0(
#17790955000
1!
1(
b000011010001 /
#17832620000
0!
0(
#17874285000
1!
1(
b000011010010 /
#17915950000
0!
0(
#17957615000
1!
1(
b000011010011 /
#17999280000
0!
0(
#18040945000
1!
1(
b000011010100 /
#18082610000
0!
0(
#18124275000
1!
1(
b000011010101 /
#18165940000
0!
0(
#18207605000
1!
1(
b000011010110 /
#18249270000
0!
0(
#18290935000
1!
1(
b000011010111 /
#18332600000
0!
0(
#18374265000
1!
1(
b000011011000 /
#18415930000
0!
0(
#18457595000
1!
1(
b000011011001 /
#18499260000
0!
0(
#18540925000
1!
1(
b000011011010 /
#18582590000
0!
0(
#18624255000
1!
1(
b000011011011 /
#18665920000
0!
0(
#18707585000
1!
1(
b000011011100 /
#18749250000
0!
0(
#18790915000
1!
1(
b000011011101 /
#18832580000
0!
0(
#18874245000
1!
1(
b000011011110 /
#18915910000
0!
0(
#18957575000
1!
1(
b000011011111 /
#18999240000
0!
0(
#19040905000
1!
1(
b000011100000 /
#19082570000
0!
0(
#19124235000
1!
1(
b000011100001 /
#19165900000
0!
0(
#19207565000
1!
1(
b000011100010 /
#19249230000
0!
0(
#19290895000
1!
1(
b000011100011 /
#19332560000
0!
0(
#19374225000
1!
1(
b000011100100 /
#19415890000
0!
0(
#19457555000
1!
1(
b000011100101 /
#19499220000
0!
0(
#19540885000
1!
1(
b000011100110 /
#19582550000
0!
0(
#19624215000
1!
1(
b000011100111 /
#19665880000
0!
0(
#19707545000
1!
1(
b000011101000 /
#19749210000
0!
0(
#19790875000
1!
1(
b000011101001 /
#19832540000
0!
0(
#19874205000
1!
1(
b000011101010 /
#19915870000
0!
0(
#19957535000
1!
1(
b000011101011 /
#19999200000
0!
0(
#20040865000
1!
1(
b000011101100 /
#20082530000
0!
0(
#20124195000
1!
1(
b000011101101 /
#20165860000
0!
0(
#20207525000
1!
1(
b000011101110 /
#20249190000
0!
0(
#20290855000
1!
1(
b000011101111 /
#20332520000
0!
0(
#20374185000
1!
1(
b000011110000 /
#20415850000
0!
0(
#20457515000
1!
1(
b000011110001 /
#20499180000
0!
0(
#20540845000
1!
1(
b000011110010 /
#20582510000
0!
0(
#20624175000
1!
1(
b000011110011 /
#20665840000
0!
0(
#20707505000
1!
1(
b000011110100 /
#20749170000
0!
0(
#20790835000
1!
1(
b000011110101 /
#20832500000
0!
0(
#20874165000
1!
1(
b000011110110 /
#20915830000
0!
0(
#20957495000
1!
1(
b000011110111 /
#20999160000
0!
0(
#21040825000
1!
1(
b000011111000 /
#21082490000
0!
0(
#21124155000
1!
1(
b000011111001 /
#21165820000
0!
0(
#21207485000
1!
1(
b000011111010 /
#21249150000
0!
0(
#21290815000
1!
1(
b000011111011 /
#21332480000
0!
0(
#21374145000
1!
1(
b000011111100 /
#21415810000
0!
0(
#21457475000
1!
1(
b000011111101 /
#21499140000
0!
0(
#21540805000
1!
1(
b000011111110 /
#21582470000
0!
0(
#21624135000
1!
1(
b000011111111 /
#21665800000
0!
0(
#21707465000
1!
1(
b000100000000 /
#21749130000
0!
0(
#21790795000
1!
1(
b000100000001 /
#21832460000
0!
0(
#21874125000
1!
1(
b000100000010 /
#21915790000
0!
0(
#21957455000
1!
1(
b000100000011 /
#21999120000
0!
0(
#22040785000
1!
1(
b000100000100 /
#22082450000
0!
0(
#22124115000
1!
1(
b000100000101 /
#22165780000
0!
0(
#22207445000
1!
1(
b000100000110 /
#22249110000
0!
0(
#22290775000
1!
1(
b000100000111 /
#22332440000
0!
0(
#22374105000
1!
1(
b000100001000 /
#22415770000
0!
0(
#22457435000
1!
1(
b000100001001 /
#22499100000
0!
0(
#22540765000
1!
1(
b000100001010 /
#22582430000
0!
0(
#22624095000
1!
1(
b000100001011 /
#22665760000
0!
0(
#22707425000
1!
1(
b000100001100 /
#22749090000
0!
0(
#22790755000
1!
1(
b000100001101 /
#22832420000
0!
0(
#22874085000
1!
1(
b000100001110 /
#22915750000
0!
0(
#22957415000
1!
1(
b000100001111 /
#22999080000
0!
0(
#23040745000
1!
1(
b000100010000 /
#23082410000
0!
0(
#23124075000
1!
1(
b000100010001 /
#23165740000
0!
0(
#23207405000
1!
1(
b000100010010 /
#23249070000
0!
0(
#23290735000
1!
1(
b000100010011 /
#23332400000
0!
0(
#23374065000
1!
1(
b000100010100 /
#23415730000
0!
0(
#23457395000
1!
1(
b000100010101 /
#23499060000
0!
0(
#23540725000
1!
1(
b000100010110 /
#23582390000
0!
0(
#23624055000
1!
1(
b000100010111 /
#23665720000
0!
0(
#23707385000
1!
1(
b000100011000 /
#23749050000
0!
0(
#23790715000
1!
1(
b000100011001 /
#23832380000
0!
0(
#23874045000
1!
1(
b000100011010 /
#23915710000
0!
0(
#23957375000
1!
1(
b000100011011 /
#23999040000
0!
0(
#24040705000
1!
1(
b000100011100 /
#24082370000
0!
0(
#24124035000
1!
1(
b000100011101 /
#24165700000
0!
0(
#24207365000
1!
1(
b000100011110 /
#24249030000
0!
0(
#24290695000
1!
1(
b000100011111 /
#24332360000
0!
0(
#24374025000
1!
1(
b000100100000 /
#24415690000
0!
0(
#24457355000
1!
1(
b000100100001 /
